Workbook

Sheet START HERE
A1: HAIRSTYLIST COMPLETE GROWTH BUNDLE
A2: Profit Calculator
A3: Know Your Numbers. Price With Confidence. Keep More Money.
A5: HOW TO USE THIS CALCULATOR
A6: Tab | B6: Sheet Name | C6: What It Does
A7: 1 | B7: 1 - Service Pricing | C7: Start here. Enter your supply costs and service durations. See your true price floor, recommended price, and margin status for every service. Identifies any service you're currently undercharging for.
A8: 2 | B8: 2 - Break-Even Tracker | C8: Enter your monthly expenses. The tracker calculates exactly how many services you need to perform each month just to cover your costs — and what every additional service earns you.
A9: 3 | B9: 3 - Service Menu Planner | C9: Your complete menu overview. Price floors auto-pull from Tab 1. Enter your current prices and see ✅ Healthy / ⚠️ Low Margin / 🚨 Below Floor status for every service at a glance.
A10: 4 | B10: 4 - Profit Goal Setter | C10: Work backward from your income goal. Enter what you want to take home and your schedule — the calculator tells you exactly how many clients per week you need and shows you the 3 levers to close any gap.
A12: COLOR CODING GUIDE
A13: Aa | B13: BLUE TEXT on light background | C13: Input cell — enter your data here
A14: Aa | B14: BLACK TEXT on white background | C14: Formula cell — calculates automatically, do not edit
A15: Aa | B15: GREEN TEXT | C15: Cross-sheet link — pulls data from another tab automatically
A17: QUICK START — DO THIS FIRST
A18: Step 1 | B18: Go to Tab 1 (Service Pricing). Enter your top 5 services — supply cost, duration, and your current price. Check the Status column immediately.
A19: Step 2 | B19: Go to Tab 2 (Break-Even). Enter all your monthly expenses. Note your break-even service count.
A20: Step 3 | B20: Go to Tab 3 (Menu Planner). Review the full menu status. Any 🚨 Below Floor services need a price fix before anything else.
A21: Step 4 | B21: Go to Tab 4 (Goal Setter). Enter your income goal and schedule. Identify which lever — ticket, volume, or days — gets you there fastest.
A24: © 2026 · Hairstylist Complete Growth Bundle · All rights reserved · For single-business use only

Sheet 1 - Service Pricing
A1: HAIRSTYLIST COMPLETE GROWTH BUNDLE
A2: TAB 1 — Service Pricing Calculator
A3: Enter your details in BLUE cells. All other cells calculate automatically. | Blue = Input Black = Formula Green = Cross-sheet link
A5: GLOBAL ASSUMPTIONS (apply to all services)
A6: Target Hourly Rate ($/hr) | B6: 65 | C6: Overhead Per Hour ($/hr) | D6: 12 | E6: Recommended Margin % | F6: 0.2
A8: SERVICE PRICING TABLE
A9: Service Name | B9: Supply Cost ($) | C9: Duration (min) | D9: Price Floor ($) | E9: Rec. Price (+20%) | F9: Your Current Price ($) | G9: Margin ($) | H9: Margin (%) | I9: Status
A10: Full Balayage | B10: 22 | C10: 210 | D10: =IF(B10="","",B10+(C10/60)*($B$6+$D$6)) -> 291.5 | E10: =IF(D10="","",D10*(1+$F$6)) -> 349.8 | F10: 280 | G10: =IF(OR(F10="",D10=""),"",F10-D10) -> -11.5 | H10: =IF(OR(F10="",F10=0),"",G10/F10) -> -0.041071429 | I10: =IF(D10="","",IF(F10<D10,"🚨 Below Floor",IF(G10/F10<$F$6,"⚠️ Low Margin","✅ Healthy"))) -> 🚨 Below Floor
A11: Root Touch-Up | B11: 8 | C11: 75 | D11: =IF(B11="","",B11+(C11/60)*($B$6+$D$6)) -> 104.25 | E11: =IF(D11="","",D11*(1+$F$6)) -> 125.1 | F11: 100 | G11: =IF(OR(F11="",D11=""),"",F11-D11) -> -4.25 | H11: =IF(OR(F11="",F11=0),"",G11/F11) -> -0.0425 | I11: =IF(D11="","",IF(F11<D11,"🚨 Below Floor",IF(G11/F11<$F$6,"⚠️ Low Margin","✅ Healthy"))) -> 🚨 Below Floor
A12: Full Highlights | B12: 18 | C12: 150 | D12: =IF(B12="","",B12+(C12/60)*($B$6+$D$6)) -> 210.5 | E12: =IF(D12="","",D12*(1+$F$6)) -> 252.6 | F12: 200 | G12: =IF(OR(F12="",D12=""),"",F12-D12) -> -10.5 | H12: =IF(OR(F12="",F12=0),"",G12/F12) -> -0.0525 | I12: =IF(D12="","",IF(F12<D12,"🚨 Below Floor",IF(G12/F12<$F$6,"⚠️ Low Margin","✅ Healthy"))) -> 🚨 Below Floor
A13: Women's Cut & Style | B13: 4 | C13: 60 | D13: =IF(B13="","",B13+(C13/60)*($B$6+$D$6)) -> 81 | E13: =IF(D13="","",D13*(1+$F$6)) -> 97.2 | F13: 80 | G13: =IF(OR(F13="",D13=""),"",F13-D13) -> -1 | H13: =IF(OR(F13="",F13=0),"",G13/F13) -> -0.0125 | I13: =IF(D13="","",IF(F13<D13,"🚨 Below Floor",IF(G13/F13<$F$6,"⚠️ Low Margin","✅ Healthy"))) -> 🚨 Below Floor
A14: Men's Cut | B14: 2 | C14: 30 | D14: =IF(B14="","",B14+(C14/60)*($B$6+$D$6)) -> 40.5 | E14: =IF(D14="","",D14*(1+$F$6)) -> 48.6 | F14: 40 | G14: =IF(OR(F14="",D14=""),"",F14-D14) -> -0.5 | H14: =IF(OR(F14="",F14=0),"",G14/F14) -> -0.0125 | I14: =IF(D14="","",IF(F14<D14,"🚨 Below Floor",IF(G14/F14<$F$6,"⚠️ Low Margin","✅ Healthy"))) -> 🚨 Below Floor
A15: Keratin Treatment | B15: 15 | C15: 150 | D15: =IF(B15="","",B15+(C15/60)*($B$6+$D$6)) -> 207.5 | E15: =IF(D15="","",D15*(1+$F$6)) -> 249 | F15: 200 | G15: =IF(OR(F15="",D15=""),"",F15-D15) -> -7.5 | H15: =IF(OR(F15="",F15=0),"",G15/F15) -> -0.0375 | I15: =IF(D15="","",IF(F15<D15,"🚨 Below Floor",IF(G15/F15<$F$6,"⚠️ Low Margin","✅ Healthy"))) -> 🚨 Below Floor
A16: Color Correction | B16: 35 | C16: 270 | D16: =IF(B16="","",B16+(C16/60)*($B$6+$D$6)) -> 381.5 | E16: =IF(D16="","",D16*(1+$F$6)) -> 457.8 | F16: 360 | G16: =IF(OR(F16="",D16=""),"",F16-D16) -> -21.5 | H16: =IF(OR(F16="",F16=0),"",G16/F16) -> -0.059722222 | I16: =IF(D16="","",IF(F16<D16,"🚨 Below Floor",IF(G16/F16<$F$6,"⚠️ Low Margin","✅ Healthy"))) -> 🚨 Below Floor
A17: Gloss / Toner | B17: 6 | C17: 45 | D17: =IF(B17="","",B17+(C17/60)*($B$6+$D$6)) -> 63.75 | E17: =IF(D17="","",D17*(1+$F$6)) -> 76.5 | F17: 60 | G17: =IF(OR(F17="",D17=""),"",F17-D17) -> -3.75 | H17: =IF(OR(F17="",F17=0),"",G17/F17) -> -0.0625 | I17: =IF(D17="","",IF(F17<D17,"🚨 Below Floor",IF(G17/F17<$F$6,"⚠️ Low Margin","✅ Healthy"))) -> 🚨 Below Floor
A18: Blowout | B18: 2 | C18: 45 | D18: =IF(B18="","",B18+(C18/60)*($B$6+$D$6)) -> 59.75 | E18: =IF(D18="","",D18*(1+$F$6)) -> 71.7 | F18: 60 | G18: =IF(OR(F18="",D18=""),"",F18-D18) -> 0.25 | H18: =IF(OR(F18="",F18=0),"",G18/F18) -> 0.0041666667 | I18: =IF(D18="","",IF(F18<D18,"🚨 Below Floor",IF(G18/F18<$F$6,"⚠️ Low Margin","✅ Healthy"))) -> ⚠️ Low Margin
A19: Deep Conditioning | B19: 8 | C19: 60 | D19: =IF(B19="","",B19+(C19/60)*($B$6+$D$6)) -> 85 | E19: =IF(D19="","",D19*(1+$F$6)) -> 102 | F19: 80 | G19: =IF(OR(F19="",D19=""),"",F19-D19) -> -5 | H19: =IF(OR(F19="",F19=0),"",G19/F19) -> -0.0625 | I19: =IF(D19="","",IF(F19<D19,"🚨 Below Floor",IF(G19/F19<$F$6,"⚠️ Low Margin","✅ Healthy"))) -> 🚨 Below Floor
D20: =IF(B20="","",B20+(C20/60)*($B$6+$D$6)) | E20: =IF(D20="","",D20*(1+$F$6)) | G20: =IF(OR(F20="",D20=""),"",F20-D20) | H20: =IF(OR(F20="",F20=0),"",G20/F20) | I20: =IF(D20="","",IF(F20<D20,"🚨 Below Floor",IF(G20/F20<$F$6,"⚠️ Low Margin","✅ Healthy")))
D21: =IF(B21="","",B21+(C21/60)*($B$6+$D$6)) | E21: =IF(D21="","",D21*(1+$F$6)) | G21: =IF(OR(F21="",D21=""),"",F21-D21) | H21: =IF(OR(F21="",F21=0),"",G21/F21) | I21: =IF(D21="","",IF(F21<D21,"🚨 Below Floor",IF(G21/F21<$F$6,"⚠️ Low Margin","✅ Healthy")))
D22: =IF(B22="","",B22+(C22/60)*($B$6+$D$6)) | E22: =IF(D22="","",D22*(1+$F$6)) | G22: =IF(OR(F22="",D22=""),"",F22-D22) | H22: =IF(OR(F22="",F22=0),"",G22/F22) | I22: =IF(D22="","",IF(F22<D22,"🚨 Below Floor",IF(G22/F22<$F$6,"⚠️ Low Margin","✅ Healthy")))
D23: =IF(B23="","",B23+(C23/60)*($B$6+$D$6)) | E23: =IF(D23="","",D23*(1+$F$6)) | G23: =IF(OR(F23="",D23=""),"",F23-D23) | H23: =IF(OR(F23="",F23=0),"",G23/F23) | I23: =IF(D23="","",IF(F23<D23,"🚨 Below Floor",IF(G23/F23<$F$6,"⚠️ Low Margin","✅ Healthy")))
D24: =IF(B24="","",B24+(C24/60)*($B$6+$D$6)) | E24: =IF(D24="","",D24*(1+$F$6)) | G24: =IF(OR(F24="",D24=""),"",F24-D24) | H24: =IF(OR(F24="",F24=0),"",G24/F24) | I24: =IF(D24="","",IF(F24<D24,"🚨 Below Floor",IF(G24/F24<$F$6,"⚠️ Low Margin","✅ Healthy")))
A27: SUMMARY
A28: Services Priced | D28: =COUNTA(A10:A24) -> 10
A29: Services Below Floor | D29: =COUNTIF(I10:I24,"*Below Floor*") -> 9
A30: Services Low Margin | D30: =COUNTIF(I10:I24,"*Low Margin*") -> 1
A31: Services Healthy | D31: =COUNTIF(I10:I24,"*Healthy*") -> 0
A32: Average Current Price | D32: =IFERROR(AVERAGEIF(F10:F24,"<>",F10:F24),"-") -> 146
A33: Average Margin % | D33: =IFERROR(AVERAGEIF(H10:H24,"<>",H10:H24),"-") -> -0.037912698

Sheet 2 - Break-Even Tracker
A1: HAIRSTYLIST COMPLETE GROWTH BUNDLE
A2: TAB 2 — Break-Even Tracker
A3: Enter your monthly expenses in BLUE cells. The tracker calculates how many services you need to break even.
A5: MONTHLY FIXED EXPENSES
A6: Expense Category | B6: Monthly Amount ($) | C6: Notes
A7: Booth Rent / Chair Rent | B7: 800
A8: Product & Supply Budget | B8: 200
A9: Software Subscriptions | B9: 60
A10: Education & Training | B10: 50
A11: Marketing Budget | B11: 40
A12: Health Insurance / Benefits | B12: 150
A13: Phone (business use portion) | B13: 30
A14: Miscellaneous / Buffer (10%) | B14: =SUM(B7:B13)*0.1 -> 133
A17: TOTAL MONTHLY EXPENSES | B17: =SUM(B7:B16) -> 1463
A19: BREAK-EVEN INPUTS
A20: Average Revenue Per Service ($) | B20: 120
A21: Working Days Per Month | B21: 20
A22: Average Clients Per Day | B22: 5
A24: BREAK-EVEN RESULTS
A25: Break-Even Services Per Month | B25: =IFERROR(CEILING(B17/B20,1),"-") -> 13
A26: Break-Even Services Per Week | B26: =IFERROR(CEILING(B17/(B20*4),1),"-") -> 4
A27: Break-Even Services Per Day | B27: =IFERROR(CEILING(B17/(B20*B21),1),"-") -> 1
A28: Total Revenue at Full Capacity | B28: =B20*B21*B22 -> 12000
A29: Profit at Full Capacity | B29: =B20*B21*B22-B17 -> 10537
A30: Days to Break-Even | B30: =IFERROR(CEILING(B17/(B20*B22),1),"-") -> 3
A31: Utilization Rate Needed | B31: =IFERROR(CEILING(B17/B20,1)/(B21*B22),"-") -> 0.13
A32: Profit Per Service Above Break-Even | B32: =B20*(1-(B17/(B20*B21*B22))) -> 105.37

Sheet 3 - Service Menu Planner
A1: HAIRSTYLIST COMPLETE GROWTH BUNDLE
A2: TAB 3 — Service Menu Planner
A3: Full menu overview. Price floors auto-link from Tab 1. Enter your current prices in BLUE. Status flags highlight where margins need attention.
A5: FULL SERVICE MENU
A6: Service Name | B6: Category | C6: Price Floor ($) | D6: Rec. Price ($) | E6: Your Price ($) | F6: Margin ($) | G6: Margin (%) | H6: Status
A7: ='1 - Service Pricing'!A10 -> Full Balayage | B7: Color | C7: ='1 - Service Pricing'!D10 -> 291.5 | D7: ='1 - Service Pricing'!E10 -> 349.8 | E7: ='1 - Service Pricing'!F10 -> 280 | F7: =IF(OR(E7="",C7=""),"",E7-C7) -> -11.5 | G7: =IF(OR(E7="",E7=0),"",F7/E7) -> -0.041071429 | H7: =IF(C7="","",IF(E7<C7,"🚨 Below Floor",IF((E7-C7)/E7<0.15,"⚠️ Low Margin","✅ Healthy"))) -> 🚨 Below Floor
A8: ='1 - Service Pricing'!A11 -> Root Touch-Up | B8: Color | C8: ='1 - Service Pricing'!D11 -> 104.25 | D8: ='1 - Service Pricing'!E11 -> 125.1 | E8: ='1 - Service Pricing'!F11 -> 100 | F8: =IF(OR(E8="",C8=""),"",E8-C8) -> -4.25 | G8: =IF(OR(E8="",E8=0),"",F8/E8) -> -0.0425 | H8: =IF(C8="","",IF(E8<C8,"🚨 Below Floor",IF((E8-C8)/E8<0.15,"⚠️ Low Margin","✅ Healthy"))) -> 🚨 Below Floor
A9: ='1 - Service Pricing'!A12 -> Full Highlights | B9: Color | C9: ='1 - Service Pricing'!D12 -> 210.5 | D9: ='1 - Service Pricing'!E12 -> 252.6 | E9: ='1 - Service Pricing'!F12 -> 200 | F9: =IF(OR(E9="",C9=""),"",E9-C9) -> -10.5 | G9: =IF(OR(E9="",E9=0),"",F9/E9) -> -0.0525 | H9: =IF(C9="","",IF(E9<C9,"🚨 Below Floor",IF((E9-C9)/E9<0.15,"⚠️ Low Margin","✅ Healthy"))) -> 🚨 Below Floor
A10: ='1 - Service Pricing'!A13 -> Women's Cut & Style | B10: Cut | C10: ='1 - Service Pricing'!D13 -> 81 | D10: ='1 - Service Pricing'!E13 -> 97.2 | E10: ='1 - Service Pricing'!F13 -> 80 | F10: =IF(OR(E10="",C10=""),"",E10-C10) -> -1 | G10: =IF(OR(E10="",E10=0),"",F10/E10) -> -0.0125 | H10: =IF(C10="","",IF(E10<C10,"🚨 Below Floor",IF((E10-C10)/E10<0.15,"⚠️ Low Margin","✅ Healthy"))) -> 🚨 Below Floor
A11: ='1 - Service Pricing'!A14 -> Men's Cut | B11: Cut | C11: ='1 - Service Pricing'!D14 -> 40.5 | D11: ='1 - Service Pricing'!E14 -> 48.6 | E11: ='1 - Service Pricing'!F14 -> 40 | F11: =IF(OR(E11="",C11=""),"",E11-C11) -> -0.5 | G11: =IF(OR(E11="",E11=0),"",F11/E11) -> -0.0125 | H11: =IF(C11="","",IF(E11<C11,"🚨 Below Floor",IF((E11-C11)/E11<0.15,"⚠️ Low Margin","✅ Healthy"))) -> 🚨 Below Floor
A12: ='1 - Service Pricing'!A15 -> Keratin Treatment | B12: Treatment | C12: ='1 - Service Pricing'!D15 -> 207.5 | D12: ='1 - Service Pricing'!E15 -> 249 | E12: ='1 - Service Pricing'!F15 -> 200 | F12: =IF(OR(E12="",C12=""),"",E12-C12) -> -7.5 | G12: =IF(OR(E12="",E12=0),"",F12/E12) -> -0.0375 | H12: =IF(C12="","",IF(E12<C12,"🚨 Below Floor",IF((E12-C12)/E12<0.15,"⚠️ Low Margin","✅ Healthy"))) -> 🚨 Below Floor
A13: ='1 - Service Pricing'!A16 -> Color Correction | B13: Color | C13: ='1 - Service Pricing'!D16 -> 381.5 | D13: ='1 - Service Pricing'!E16 -> 457.8 | E13: ='1 - Service Pricing'!F16 -> 360 | F13: =IF(OR(E13="",C13=""),"",E13-C13) -> -21.5 | G13: =IF(OR(E13="",E13=0),"",F13/E13) -> -0.059722222 | H13: =IF(C13="","",IF(E13<C13,"🚨 Below Floor",IF((E13-C13)/E13<0.15,"⚠️ Low Margin","✅ Healthy"))) -> 🚨 Below Floor
A14: ='1 - Service Pricing'!A17 -> Gloss / Toner | B14: Color | C14: ='1 - Service Pricing'!D17 -> 63.75 | D14: ='1 - Service Pricing'!E17 -> 76.5 | E14: ='1 - Service Pricing'!F17 -> 60 | F14: =IF(OR(E14="",C14=""),"",E14-C14) -> -3.75 | G14: =IF(OR(E14="",E14=0),"",F14/E14) -> -0.0625 | H14: =IF(C14="","",IF(E14<C14,"🚨 Below Floor",IF((E14-C14)/E14<0.15,"⚠️ Low Margin","✅ Healthy"))) -> 🚨 Below Floor
A15: ='1 - Service Pricing'!A18 -> Blowout | B15: Style | C15: ='1 - Service Pricing'!D18 -> 59.75 | D15: ='1 - Service Pricing'!E18 -> 71.7 | E15: ='1 - Service Pricing'!F18 -> 60 | F15: =IF(OR(E15="",C15=""),"",E15-C15) -> 0.25 | G15: =IF(OR(E15="",E15=0),"",F15/E15) -> 0.0041666667 | H15: =IF(C15="","",IF(E15<C15,"🚨 Below Floor",IF((E15-C15)/E15<0.15,"⚠️ Low Margin","✅ Healthy"))) -> ⚠️ Low Margin
A16: ='1 - Service Pricing'!A19 -> Deep Conditioning | B16: Treatment | C16: ='1 - Service Pricing'!D19 -> 85 | D16: ='1 - Service Pricing'!E19 -> 102 | E16: ='1 - Service Pricing'!F19 -> 80 | F16: =IF(OR(E16="",C16=""),"",E16-C16) -> -5 | G16: =IF(OR(E16="",E16=0),"",F16/E16) -> -0.0625 | H16: =IF(C16="","",IF(E16<C16,"🚨 Below Floor",IF((E16-C16)/E16<0.15,"⚠️ Low Margin","✅ Healthy"))) -> 🚨 Below Floor
A17: ='1 - Service Pricing'!A20 -> 0 | C17: ='1 - Service Pricing'!D20 | D17: ='1 - Service Pricing'!E20 | E17: ='1 - Service Pricing'!F20 -> 0 | F17: =IF(OR(E17="",C17=""),"",E17-C17) | G17: =IF(OR(E17="",E17=0),"",F17/E17) | H17: =IF(C17="","",IF(E17<C17,"🚨 Below Floor",IF((E17-C17)/E17<0.15,"⚠️ Low Margin","✅ Healthy")))
A18: ='1 - Service Pricing'!A21 -> 0 | C18: ='1 - Service Pricing'!D21 | D18: ='1 - Service Pricing'!E21 | E18: ='1 - Service Pricing'!F21 -> 0 | F18: =IF(OR(E18="",C18=""),"",E18-C18) | G18: =IF(OR(E18="",E18=0),"",F18/E18) | H18: =IF(C18="","",IF(E18<C18,"🚨 Below Floor",IF((E18-C18)/E18<0.15,"⚠️ Low Margin","✅ Healthy")))
A19: ='1 - Service Pricing'!A22 -> 0 | C19: ='1 - Service Pricing'!D22 | D19: ='1 - Service Pricing'!E22 | E19: ='1 - Service Pricing'!F22 -> 0 | F19: =IF(OR(E19="",C19=""),"",E19-C19) | G19: =IF(OR(E19="",E19=0),"",F19/E19) | H19: =IF(C19="","",IF(E19<C19,"🚨 Below Floor",IF((E19-C19)/E19<0.15,"⚠️ Low Margin","✅ Healthy")))
A20: ='1 - Service Pricing'!A23 -> 0 | C20: ='1 - Service Pricing'!D23 | D20: ='1 - Service Pricing'!E23 | E20: ='1 - Service Pricing'!F23 -> 0 | F20: =IF(OR(E20="",C20=""),"",E20-C20) | G20: =IF(OR(E20="",E20=0),"",F20/E20) | H20: =IF(C20="","",IF(E20<C20,"🚨 Below Floor",IF((E20-C20)/E20<0.15,"⚠️ Low Margin","✅ Healthy")))
A21: ='1 - Service Pricing'!A24 -> 0 | C21: ='1 - Service Pricing'!D24 | D21: ='1 - Service Pricing'!E24 | E21: ='1 - Service Pricing'!F24 -> 0 | F21: =IF(OR(E21="",C21=""),"",E21-C21) | G21: =IF(OR(E21="",E21=0),"",F21/E21) | H21: =IF(C21="","",IF(E21<C21,"🚨 Below Floor",IF((E21-C21)/E21<0.15,"⚠️ Low Margin","✅ Healthy")))
F22: =IF(OR(E22="",C22=""),"",E22-C22) | G22: =IF(OR(E22="",E22=0),"",F22/E22) | H22: =IF(C22="","",IF(E22<C22,"🚨 Below Floor",IF((E22-C22)/E22<0.15,"⚠️ Low Margin","✅ Healthy")))
F23: =IF(OR(E23="",C23=""),"",E23-C23) | G23: =IF(OR(E23="",E23=0),"",F23/E23) | H23: =IF(C23="","",IF(E23<C23,"🚨 Below Floor",IF((E23-C23)/E23<0.15,"⚠️ Low Margin","✅ Healthy")))
F24: =IF(OR(E24="",C24=""),"",E24-C24) | G24: =IF(OR(E24="",E24=0),"",F24/E24) | H24: =IF(C24="","",IF(E24<C24,"🚨 Below Floor",IF((E24-C24)/E24<0.15,"⚠️ Low Margin","✅ Healthy")))
F25: =IF(OR(E25="",C25=""),"",E25-C25) | G25: =IF(OR(E25="",E25=0),"",F25/E25) | H25: =IF(C25="","",IF(E25<C25,"🚨 Below Floor",IF((E25-C25)/E25<0.15,"⚠️ Low Margin","✅ Healthy")))
F26: =IF(OR(E26="",C26=""),"",E26-C26) | G26: =IF(OR(E26="",E26=0),"",F26/E26) | H26: =IF(C26="","",IF(E26<C26,"🚨 Below Floor",IF((E26-C26)/E26<0.15,"⚠️ Low Margin","✅ Healthy")))
A29: MENU SUMMARY
A30: Total Services on Menu | C30: =COUNTA(A7:A26) -> 15
A31: 🚨 Below Floor | C31: =COUNTIF(H7:H26,"*Below Floor*") -> 9
A32: ⚠️ Low Margin | C32: =COUNTIF(H7:H26,"*Low Margin*") -> 1
A33: ✅ Healthy | C33: =COUNTIF(H7:H26,"*Healthy*") -> 0
A34: Average Price | C34: =IFERROR(AVERAGEIF(E7:E26,">0",E7:E26),"-") -> 146
A35: Average Margin % | C35: =IFERROR(AVERAGEIF(G7:G26,"<>",G7:G26),"-") -> -0.037912698
A36: Highest Margin Service | C36: =IFERROR(INDEX(A7:A26,MATCH(MAX(G7:G26),G7:G26,0)),"-") -> Blowout
A37: Lowest Margin Service | C37: =IFERROR(INDEX(A7:A26,MATCH(MIN(IF(G7:G26<>"",G7:G26)),G7:G26,0)),"-") -> -

Sheet 4 - Profit Goal Setter
A1: HAIRSTYLIST COMPLETE GROWTH BUNDLE
A2: TAB 4 — Monthly Profit Goal Setter
A3: Start with your income goal. This tab works backward to tell you exactly what you need to do each week to get there.
A5: STEP 1 — YOUR INCOME GOAL
A6: Target Take-Home Income ($/month) | B6: 5000
A7: Total Monthly Expenses ($) | B7: ='2 - Break-Even Tracker'!B17 -> 1463
A8: Target Gross Revenue Needed ($/month) | B8: =B6+B7 -> 6463
A10: STEP 2 — YOUR SCHEDULE
A11: Working Days Per Week | B11: 4
A12: Appointment Hours Per Day | B12: 7
A13: Average Appointment Length (min) | B13: 75
A14: Average Revenue Per Service ($) | B14: 120
A16: STEP 3 — WHAT YOU NEED TO DO
A17: Available Appointments Per Month | B17: =FLOOR(B12*60/B13,1)*B11*4 -> 80
A18: Total Available Monthly Revenue | B18: =B17*B14 -> 9600
A19: Clients Needed Per Month | B19: =CEILING(B8/B14,1) -> 54
A20: Clients Needed Per Week | B20: =CEILING(B19/4,1) -> 14
A21: Clients Needed Per Day | B21: =CEILING(B20/B11,1) -> 4
A22: Required Utilization Rate | B22: =IFERROR(B19/B17,"-") -> 0.675
A23: Daily Revenue Target | B23: =B8/(B11*4) -> 403.9375
A24: Weekly Revenue Target | B24: =B8/4 -> 1615.75
A26: GAP ANALYSIS — THE 3 LEVERS
A27: Lever | B27: Current Pace | C27: Needed | D27: Gap
A28: Avg Ticket (raise prices) | B28: =B14 -> 120 | C28: =IFERROR(B8/B19,"-") -> 119.68519 | D28: =IFERROR(C28-B28,"-") -> -0.31481481
A29: Clients Per Month (fill books) | B29: =B11*4*FLOOR(B12*60/B13,1)*0.75 -> 60 | C29: =B19 -> 54 | D29: =IFERROR(C29-B29,"-") -> -6
A30: Working Days Per Week | B30: =B11 -> 4 | C30: =IFERROR(CEILING(B19/FLOOR(B12*60/B13,1)/4,0.5),"-") -> 3 | D30: =IFERROR(C30-B30,"-") -> -1
